npc_stim/__init__.py
npc_stim/py.typed
npc_stim/running.py
npc_stim/stim.py
npc_stim/types.py
npc_stim-0.1.14.dist-info/licenses/LICENSE
npc_stim-0.1.14.dist-info/METADATA
npc_stim-0.1.14.dist-info/WHEEL
npc_stim-0.1.14.dist-info/top_level.txt
npc_stim-0.1.14.dist-info/RECORD
