Metadata-Version: 2.4
Name: npc-stim
Version: 0.1.14
Summary: Tools for accessing and processing stim data, compatible with data in the cloud.
Author-email: Ben Hardcastle <ben.hardcastle@alleninstitue.org>
License: MIT
Project-URL: Repository, https://github.com/AllenInstitute/npc_stim
Project-URL: Issues, https://github.com/AllenInstitute/npc_stim/issues
Classifier: Development Status :: 3 - Alpha
Classifier: Programming Language :: Python :: 3
Classifier: Programming Language :: Python :: 3.9
Classifier: Programming Language :: Python :: 3.10
Classifier: Programming Language :: Python :: 3.11
Classifier: License :: OSI Approved :: MIT License
Classifier: Operating System :: Microsoft :: Windows
Classifier: Operating System :: POSIX :: Linux
Requires-Python: >=3.9
License-File: LICENSE
Requires-Dist: npc-sync>=0.1.19
Requires-Dist: npc_io>=0.1.26
Requires-Dist: npc-session>=0.1.33
Requires-Dist: scipy>=1.12.0
Dynamic: license-file
